AutoEMA/AutoEMA.py
AutoEMA-1.1.dist-info/LICENSE
AutoEMA-1.1.dist-info/METADATA
AutoEMA-1.1.dist-info/WHEEL
AutoEMA-1.1.dist-info/top_level.txt
AutoEMA-1.1.dist-info/RECORD
