Metadata-Version: 2.1
Name: AutoEMA
Version: 1.1
Summary: Automated Experimental Modal Analysis using Bayesian Optimization
Home-page: https://github.com/leo-beck/AutoEMA
Author: Leopold Beck
Author-email: l.beck@tum.de
Keywords: EMA,modal,analysis,automated,mechanics,bayes,bayesian,optimization
Requires-Python: >=3.7, <4
License-File: LICENSE
Requires-Dist: matplotlib (>=3.5.3)
Requires-Dist: numpy (>=1.0)
Requires-Dist: scikit-learn (>=1.1.2)
Requires-Dist: scipy (==1.7.2)
Requires-Dist: bayesian-optimization (>=1.2.0)
Requires-Dist: sdypy-EMA (>=0.24)
